srem/__init__.py
srem/srem.py
srem-1.0.1.dist-info/LICENSE
srem-1.0.1.dist-info/METADATA
srem-1.0.1.dist-info/WHEEL
srem-1.0.1.dist-info/top_level.txt
srem-1.0.1.dist-info/RECORD
