Metadata-Version: 2.1
Name: srem
Version: 1.0.1
Summary: A Simplified and Robust Surface Reflectance Estimation Method for Satellite Imagery
Home-page: https://github.com/oyam/srem
Author: Taiki Oyama
Author-email: oyamat4@gmail.com
License: MIT License
Platform: UNKNOWN
Classifier: License :: OSI Approved :: MIT License
Classifier: Programming Language :: Python :: 3.6
Classifier: Programming Language :: Python :: 3.7
Classifier: Programming Language :: Python :: 3.8
Requires-Python: >=3.6
Requires-Dist: numpy (>=1.7)
Provides-Extra: test
Requires-Dist: flake8 ; extra == 'test'
Requires-Dist: mypy ; extra == 'test'
Requires-Dist: pytest (>=5.3) ; extra == 'test'
